ceviche/__init__.py
ceviche/constants.py
ceviche/derivatives.py
ceviche/fdfd.py
ceviche/fdtd.py
ceviche/jacobians.py
ceviche/modes.py
ceviche/optimizers.py
ceviche/primitives.py
ceviche/solvers.py
ceviche/sources.py
ceviche/utils.py
ceviche/viz.py
ceviche-0.1.2.dist-info/LICENSE
ceviche-0.1.2.dist-info/METADATA
ceviche-0.1.2.dist-info/WHEEL
ceviche-0.1.2.dist-info/top_level.txt
ceviche-0.1.2.dist-info/RECORD
