Metadata-Version: 2.1
Name: ceviche
Version: 0.1.2
Summary: Ceviche
Home-page: https://github.com/twhughes/ceviche
Author: Tyler Hughes
Author-email: tylerwhughes91@gmail.com
License: UNKNOWN
Platform: UNKNOWN
Classifier: Programming Language :: Python :: 3
Classifier: License :: OSI Approved :: MIT License
Classifier: Operating System :: OS Independent
Requires-Dist: numpy (>=1.16.2)
Requires-Dist: scipy (>=1.2.1)
Requires-Dist: matplotlib (>=3.0.3)
Requires-Dist: autograd (>=1.3)
Requires-Dist: pyMKL (>=0.0.3)
